{
  "title": "coef_mean",
  "data": [
    {
      "label": "y_th_100.0",
      "data": [
        {
          "x": 0,
          "y": 0.1606355117390855
        },
        {
          "x": 1,
          "y": 0.3222532379660027
        },
        {
          "x": 2,
          "y": 0.3999177801454863
        },
        {
          "x": 3,
          "y": 0.4219644325271375
        },
        {
          "x": 4,
          "y": 0.4554072883759084
        },
        {
          "x": 5,
          "y": 0.5862446154391231
        },
        {
          "x": 6,
          "y": 0.6301066562738498
        },
        {
          "x": 7,
          "y": 0.6154583479836255
        },
        {
          "x": 8,
          "y": 0.6432762598036611
        },
        {
          "x": 9,
          "y": 0.6641761971252137
        },
        {
          "x": 10,
          "y": 0.707472841785957
        },
        {
          "x": 11,
          "y": 0.711453464428496
        },
        {
          "x": 12,
          "y": 0.7174386651358892
        },
        {
          "x": 13,
          "y": 0.7269574353735171
        },
        {
          "x": 14,
          "y": 0.7330052599711291
        },
        {
          "x": 15,
          "y": 0.7535552926792382
        },
        {
          "x": 16,
          "y": 0.759634067089917
        },
        {
          "x": 17,
          "y": 0.767123105073754
        },
        {
          "x": 18,
          "y": 0.7715810400542086
        },
        {
          "x": 19,
          "y": 0.7763232302995683
        },
        {
          "x": 20,
          "y": 0.7995474461068526
        },
        {
          "x": 21,
          "y": 0.8091308305063754
        },
        {
          "x": 22,
          "y": 0.8716513675025876
        },
        {
          "x": 23,
          "y": 0.9410601708144344
        },
        {
          "x": 24,
          "y": 0.9657342089974316
        },
        {
          "x": 25,
          "y": 3.331980339545126
        },
        {
          "x": 26,
          "y": 3.366584771015784
        },
        {
          "x": 27,
          "y": 3.3765125932459554
        },
        {
          "x": 28,
          "y": 3.4050288098046684
        },
        {
          "x": 29,
          "y": 3.4536315392737045
        },
        {
          "x": 30,
          "y": 6.395266848058349
        },
        {
          "x": 31,
          "y": 6.484798562448696
        },
        {
          "x": 32,
          "y": 6.497772878656114
        },
        {
          "x": 33,
          "y": 6.506835902254636
        },
        {
          "x": 34,
          "y": 6.598564366717579
        },
        {
          "x": 35,
          "y": 9.198508906917132
        },
        {
          "x": 36,
          "y": 9.195061313939831
        },
        {
          "x": 37,
          "y": 9.195821157645035
        },
        {
          "x": 38,
          "y": 9.195744913776544
        },
        {
          "x": 39,
          "y": 9.201893394054371
        },
        {
          "x": 40,
          "y": 9.47169053461528
        },
        {
          "x": 41,
          "y": 9.471020012095456
        },
        {
          "x": 42,
          "y": 9.47083866941927
        },
        {
          "x": 43,
          "y": 9.4707865584172
        },
        {
          "x": 44,
          "y": 9.470352661175966
        },
        {
          "x": 45,
          "y": 9.426487719128584
        },
        {
          "x": 46,
          "y": 9.426534113520958
        },
        {
          "x": 47,
          "y": 9.426534602771282
        },
        {
          "x": 48,
          "y": 9.426534440411116
        },
        {
          "x": 49,
          "y": 9.426534440411116
        }
      ]
    },
    {
      "label": "y_th_1000.0",
      "data": [
        {
          "x": 0,
          "y": 0.1606355117390855
        },
        {
          "x": 1,
          "y": 0.3222532379660027
        },
        {
          "x": 2,
          "y": 0.3999177801454863
        },
        {
          "x": 3,
          "y": 0.4219644325271375
        },
        {
          "x": 4,
          "y": 0.4554072883759084
        },
        {
          "x": 5,
          "y": 0.5862446154391231
        },
        {
          "x": 6,
          "y": 0.6301066562738498
        },
        {
          "x": 7,
          "y": 0.6154583479836255
        },
        {
          "x": 8,
          "y": 0.6432762598036611
        },
        {
          "x": 9,
          "y": 0.6641761971252137
        },
        {
          "x": 10,
          "y": 0.707472841785957
        },
        {
          "x": 11,
          "y": 0.711453464428496
        },
        {
          "x": 12,
          "y": 0.7174386651358892
        },
        {
          "x": 13,
          "y": 0.7269574353735171
        },
        {
          "x": 14,
          "y": 0.7330052599711291
        },
        {
          "x": 15,
          "y": 0.7535552926792382
        },
        {
          "x": 16,
          "y": 0.759634067089917
        },
        {
          "x": 17,
          "y": 0.767123105073754
        },
        {
          "x": 18,
          "y": 0.7715810400542086
        },
        {
          "x": 19,
          "y": 0.7763232302995683
        },
        {
          "x": 20,
          "y": 0.7995474461068526
        },
        {
          "x": 21,
          "y": 0.8091308305063754
        },
        {
          "x": 22,
          "y": 0.8716513675025876
        },
        {
          "x": 23,
          "y": 0.9410601708144344
        },
        {
          "x": 24,
          "y": 0.9657342089974316
        },
        {
          "x": 25,
          "y": 3.331980339545126
        },
        {
          "x": 26,
          "y": 3.366584771015784
        },
        {
          "x": 27,
          "y": 3.3765125932459554
        },
        {
          "x": 28,
          "y": 3.4050288098046684
        },
        {
          "x": 29,
          "y": 3.4536315392737045
        },
        {
          "x": 30,
          "y": 6.395266848058349
        },
        {
          "x": 31,
          "y": 6.484798562448696
        },
        {
          "x": 32,
          "y": 6.497772878656114
        },
        {
          "x": 33,
          "y": 6.506835902254636
        },
        {
          "x": 34,
          "y": 6.598564366717579
        },
        {
          "x": 35,
          "y": 9.198508906917132
        },
        {
          "x": 36,
          "y": 9.195061313939831
        },
        {
          "x": 37,
          "y": 9.195821157645035
        },
        {
          "x": 38,
          "y": 9.195744913776544
        },
        {
          "x": 39,
          "y": 9.201893394054371
        },
        {
          "x": 40,
          "y": 9.47169053461528
        },
        {
          "x": 41,
          "y": 9.471020012095456
        },
        {
          "x": 42,
          "y": 9.47083866941927
        },
        {
          "x": 43,
          "y": 9.4707865584172
        },
        {
          "x": 44,
          "y": 9.470352661175966
        },
        {
          "x": 45,
          "y": 9.426487719128584
        },
        {
          "x": 46,
          "y": 9.426534113520958
        },
        {
          "x": 47,
          "y": 9.426534602771282
        },
        {
          "x": 48,
          "y": 9.426534440411116
        },
        {
          "x": 49,
          "y": 9.426534440411116
        }
      ]
    },
    {
      "label": "y_th_10000.0",
      "data": [
        {
          "x": 0,
          "y": 0.1606355117390855
        },
        {
          "x": 1,
          "y": 0.3222532379660027
        },
        {
          "x": 2,
          "y": 0.3999177801454863
        },
        {
          "x": 3,
          "y": 0.4219644325271375
        },
        {
          "x": 4,
          "y": 0.4554072883759084
        },
        {
          "x": 5,
          "y": 0.5862446154391231
        },
        {
          "x": 6,
          "y": 0.6301066562738498
        },
        {
          "x": 7,
          "y": 0.6154583479836255
        },
        {
          "x": 8,
          "y": 0.6432762598036611
        },
        {
          "x": 9,
          "y": 0.6641761971252137
        },
        {
          "x": 10,
          "y": 0.707472841785957
        },
        {
          "x": 11,
          "y": 0.711453464428496
        },
        {
          "x": 12,
          "y": 0.7174386651358892
        },
        {
          "x": 13,
          "y": 0.7269574353735171
        },
        {
          "x": 14,
          "y": 0.7330052599711291
        },
        {
          "x": 15,
          "y": 0.7535552926792382
        },
        {
          "x": 16,
          "y": 0.759634067089917
        },
        {
          "x": 17,
          "y": 0.767123105073754
        },
        {
          "x": 18,
          "y": 0.7715810400542086
        },
        {
          "x": 19,
          "y": 0.7763232302995683
        },
        {
          "x": 20,
          "y": 0.7995474461068526
        },
        {
          "x": 21,
          "y": 0.8091308305063754
        },
        {
          "x": 22,
          "y": 0.8716513675025876
        },
        {
          "x": 23,
          "y": 0.9410601708144344
        },
        {
          "x": 24,
          "y": 0.9657342089974316
        },
        {
          "x": 25,
          "y": 3.331980339545126
        },
        {
          "x": 26,
          "y": 3.366584771015784
        },
        {
          "x": 27,
          "y": 3.3765125932459554
        },
        {
          "x": 28,
          "y": 3.4050288098046684
        },
        {
          "x": 29,
          "y": 3.4536315392737045
        },
        {
          "x": 30,
          "y": 6.395266848058349
        },
        {
          "x": 31,
          "y": 6.484798562448696
        },
        {
          "x": 32,
          "y": 6.497772878656114
        },
        {
          "x": 33,
          "y": 6.506835902254636
        },
        {
          "x": 34,
          "y": 6.598564366717579
        },
        {
          "x": 35,
          "y": 9.198508906917132
        },
        {
          "x": 36,
          "y": 9.195061313939831
        },
        {
          "x": 37,
          "y": 9.195821157645035
        },
        {
          "x": 38,
          "y": 9.195744913776544
        },
        {
          "x": 39,
          "y": 9.201893394054371
        },
        {
          "x": 40,
          "y": 9.47169053461528
        },
        {
          "x": 41,
          "y": 9.471020012095456
        },
        {
          "x": 42,
          "y": 9.47083866941927
        },
        {
          "x": 43,
          "y": 9.4707865584172
        },
        {
          "x": 44,
          "y": 9.470352661175966
        },
        {
          "x": 45,
          "y": 9.426487719128584
        },
        {
          "x": 46,
          "y": 9.426534113520958
        },
        {
          "x": 47,
          "y": 9.426534602771282
        },
        {
          "x": 48,
          "y": 9.426534440411116
        },
        {
          "x": 49,
          "y": 9.426534440411116
        }
      ]
    }
  ]
}