{
  "title": "reg",
  "data": [
    {
      "label": "seed_147",
      "data": [
        {
          "x": 0,
          "y": 6.229135676952499
        },
        {
          "x": 1,
          "y": 9.357901634931824
        },
        {
          "x": 2,
          "y": 14.193519400418182
        },
        {
          "x": 3,
          "y": 15.186612660574625
        },
        {
          "x": 4,
          "y": 16.898060144847808
        },
        {
          "x": 5,
          "y": 17.892927145620295
        },
        {
          "x": 6,
          "y": 18.57983568556672
        },
        {
          "x": 7,
          "y": 18.46836006176855
        },
        {
          "x": 8,
          "y": 17.701593647658505
        },
        {
          "x": 9,
          "y": 17.235292770953865
        },
        {
          "x": 10,
          "y": 17.159927927407537
        },
        {
          "x": 11,
          "y": 17.239698566547613
        },
        {
          "x": 12,
          "y": 17.3231293851025
        },
        {
          "x": 13,
          "y": 17.550536499460883
        },
        {
          "x": 14,
          "y": 17.55317840930705
        },
        {
          "x": 15,
          "y": 17.537847828585512
        },
        {
          "x": 16,
          "y": 16.91448386820935
        },
        {
          "x": 17,
          "y": 16.250365149585082
        },
        {
          "x": 18,
          "y": 16.352565880549122
        },
        {
          "x": 19,
          "y": 16.508406663988342
        },
        {
          "x": 20,
          "y": 16.650559055476673
        },
        {
          "x": 21,
          "y": 16.672614323186632
        },
        {
          "x": 22,
          "y": 16.668469610211723
        },
        {
          "x": 23,
          "y": 16.757855423807342
        },
        {
          "x": 24,
          "y": 16.878971570304522
        },
        {
          "x": 25,
          "y": 16.716096489713202
        },
        {
          "x": 26,
          "y": 16.59819727623366
        },
        {
          "x": 27,
          "y": 16.664639136223265
        },
        {
          "x": 28,
          "y": 16.773278590923788
        },
        {
          "x": 29,
          "y": 17.048038562261745
        },
        {
          "x": 30,
          "y": 17.10703501966766
        },
        {
          "x": 31,
          "y": 17.138007743880536
        },
        {
          "x": 32,
          "y": 17.160421824198785
        },
        {
          "x": 33,
          "y": 17.185341481273714
        },
        {
          "x": 34,
          "y": 17.29298132922477
        },
        {
          "x": 35,
          "y": 17.336879288223017
        },
        {
          "x": 36,
          "y": 17.38882068600148
        },
        {
          "x": 37,
          "y": 17.516272139745077
        },
        {
          "x": 38,
          "y": 17.42144657442164
        },
        {
          "x": 39,
          "y": 17.335360153510887
        },
        {
          "x": 40,
          "y": 17.283106435888914
        },
        {
          "x": 41,
          "y": 17.265330726517202
        },
        {
          "x": 42,
          "y": 16.979900712627092
        },
        {
          "x": 43,
          "y": 16.769305120187536
        },
        {
          "x": 44,
          "y": 16.68871739687099
        },
        {
          "x": 45,
          "y": 16.74814123742243
        },
        {
          "x": 46,
          "y": 16.84919692560284
        },
        {
          "x": 47,
          "y": 16.798182345062614
        },
        {
          "x": 48,
          "y": 16.766876519957588
        },
        {
          "x": 49,
          "y": 16.62953188109465
        }
      ]
    },
    {
      "label": "seed_9",
      "data": [
        {
          "x": 0,
          "y": 7.716582147750582
        },
        {
          "x": 1,
          "y": 12.422929622857117
        },
        {
          "x": 2,
          "y": 11.697091792112076
        },
        {
          "x": 3,
          "y": 12.63646588955507
        },
        {
          "x": 4,
          "y": 12.41903679640818
        },
        {
          "x": 5,
          "y": 12.715585225890528
        },
        {
          "x": 6,
          "y": 12.844538248670544
        },
        {
          "x": 7,
          "y": 12.947170262518494
        },
        {
          "x": 8,
          "y": 12.720814493674643
        },
        {
          "x": 9,
          "y": 12.439409230444472
        },
        {
          "x": 10,
          "y": 12.463338865227657
        },
        {
          "x": 11,
          "y": 12.319082055625314
        },
        {
          "x": 12,
          "y": 12.402172984918424
        },
        {
          "x": 13,
          "y": 12.991244817873334
        },
        {
          "x": 14,
          "y": 13.274834118014322
        },
        {
          "x": 15,
          "y": 13.318095778732316
        },
        {
          "x": 16,
          "y": 13.501392258169671
        },
        {
          "x": 17,
          "y": 13.565107117956956
        },
        {
          "x": 18,
          "y": 13.59752379259671
        },
        {
          "x": 19,
          "y": 13.69349865026697
        },
        {
          "x": 20,
          "y": 13.705112161746564
        },
        {
          "x": 21,
          "y": 13.753814044345088
        },
        {
          "x": 22,
          "y": 13.786890108602812
        },
        {
          "x": 23,
          "y": 13.805789576762017
        },
        {
          "x": 24,
          "y": 13.824139068888284
        },
        {
          "x": 25,
          "y": 13.81285809109833
        },
        {
          "x": 26,
          "y": 13.80535057265882
        },
        {
          "x": 27,
          "y": 13.776561671788244
        },
        {
          "x": 28,
          "y": 13.770068799526625
        },
        {
          "x": 29,
          "y": 13.772933213038517
        },
        {
          "x": 30,
          "y": 13.76654258903433
        },
        {
          "x": 31,
          "y": 13.7578876122289
        },
        {
          "x": 32,
          "y": 13.74535117148779
        },
        {
          "x": 33,
          "y": 13.728948097921148
        },
        {
          "x": 34,
          "y": 13.722020397615973
        },
        {
          "x": 35,
          "y": 13.717266579409248
        },
        {
          "x": 36,
          "y": 13.695800163846863
        },
        {
          "x": 37,
          "y": 13.67961582892664
        },
        {
          "x": 38,
          "y": 13.67603832372968
        },
        {
          "x": 39,
          "y": 13.69029914706841
        },
        {
          "x": 40,
          "y": 13.683060315339992
        },
        {
          "x": 41,
          "y": 13.67417569617908
        },
        {
          "x": 42,
          "y": 13.657223494680656
        },
        {
          "x": 43,
          "y": 13.658805569439505
        },
        {
          "x": 44,
          "y": 13.6506701894618
        },
        {
          "x": 45,
          "y": 13.658274309213938
        },
        {
          "x": 46,
          "y": 13.659799078229051
        },
        {
          "x": 47,
          "y": 13.675178480924068
        },
        {
          "x": 48,
          "y": 13.682222385077722
        },
        {
          "x": 49,
          "y": 13.679198974956089
        }
      ]
    },
    {
      "label": "seed_124",
      "data": [
        {
          "x": 0,
          "y": 6.1703458344242605
        },
        {
          "x": 1,
          "y": 8.249517909391633
        },
        {
          "x": 2,
          "y": 13.43684499054824
        },
        {
          "x": 3,
          "y": 14.27192525084448
        },
        {
          "x": 4,
          "y": 14.709724494958216
        },
        {
          "x": 5,
          "y": 14.635727461273298
        },
        {
          "x": 6,
          "y": 15.801014148398409
        },
        {
          "x": 7,
          "y": 16.14739414059232
        },
        {
          "x": 8,
          "y": 16.187251184092897
        },
        {
          "x": 9,
          "y": 16.234783483278594
        },
        {
          "x": 10,
          "y": 16.31980492295147
        },
        {
          "x": 11,
          "y": 16.349361839931078
        },
        {
          "x": 12,
          "y": 16.487018819326522
        },
        {
          "x": 13,
          "y": 16.56118682638027
        },
        {
          "x": 14,
          "y": 16.72617290782434
        },
        {
          "x": 15,
          "y": 16.829905396517198
        },
        {
          "x": 16,
          "y": 16.87278522605787
        },
        {
          "x": 17,
          "y": 17.099323831200635
        },
        {
          "x": 18,
          "y": 17.17476389081722
        },
        {
          "x": 19,
          "y": 17.16488504875612
        },
        {
          "x": 20,
          "y": 17.099388971135852
        },
        {
          "x": 21,
          "y": 17.00722297175865
        },
        {
          "x": 22,
          "y": 16.97835678303708
        },
        {
          "x": 23,
          "y": 16.928019573535153
        },
        {
          "x": 24,
          "y": 16.668556871973774
        },
        {
          "x": 25,
          "y": 16.383799904251998
        },
        {
          "x": 26,
          "y": 16.286713875763223
        },
        {
          "x": 27,
          "y": 16.240720446355834
        },
        {
          "x": 28,
          "y": 16.25103961926462
        },
        {
          "x": 29,
          "y": 16.274649588519253
        },
        {
          "x": 30,
          "y": 16.291593895791014
        },
        {
          "x": 31,
          "y": 16.38462113614566
        },
        {
          "x": 32,
          "y": 16.54926261931432
        },
        {
          "x": 33,
          "y": 16.56328233924043
        },
        {
          "x": 34,
          "y": 16.7495484996547
        },
        {
          "x": 35,
          "y": 17.028356660243563
        },
        {
          "x": 36,
          "y": 17.22765741621436
        },
        {
          "x": 37,
          "y": 17.323358086904342
        },
        {
          "x": 38,
          "y": 17.444400216151617
        },
        {
          "x": 39,
          "y": 17.629359282320344
        },
        {
          "x": 40,
          "y": 17.61932344270933
        },
        {
          "x": 41,
          "y": 17.699154250384595
        },
        {
          "x": 42,
          "y": 17.6801303304634
        },
        {
          "x": 43,
          "y": 17.643622449608024
        },
        {
          "x": 44,
          "y": 17.478649780393006
        },
        {
          "x": 45,
          "y": 17.404846343104897
        },
        {
          "x": 46,
          "y": 17.350246760866003
        },
        {
          "x": 47,
          "y": 17.27466762028468
        },
        {
          "x": 48,
          "y": 17.270087274635085
        },
        {
          "x": 49,
          "y": 17.322208797927207
        }
      ]
    },
    {
      "label": "seed_32",
      "data": [
        {
          "x": 0,
          "y": 4.930328671678774
        },
        {
          "x": 1,
          "y": 9.691996134450712
        },
        {
          "x": 2,
          "y": 12.541451903079665
        },
        {
          "x": 3,
          "y": 14.202520557871626
        },
        {
          "x": 4,
          "y": 14.347135263064974
        },
        {
          "x": 5,
          "y": 13.789232718744527
        },
        {
          "x": 6,
          "y": 13.67103864916939
        },
        {
          "x": 7,
          "y": 13.78386977916041
        },
        {
          "x": 8,
          "y": 13.897499456423738
        },
        {
          "x": 9,
          "y": 13.626947378062043
        },
        {
          "x": 10,
          "y": 13.86224484879508
        },
        {
          "x": 11,
          "y": 14.062346795374214
        },
        {
          "x": 12,
          "y": 13.915149823464692
        },
        {
          "x": 13,
          "y": 14.39374328020256
        },
        {
          "x": 14,
          "y": 15.126054896384804
        },
        {
          "x": 15,
          "y": 14.818906664318362
        },
        {
          "x": 16,
          "y": 15.181503262555657
        },
        {
          "x": 17,
          "y": 15.543303205846383
        },
        {
          "x": 18,
          "y": 15.77303920772188
        },
        {
          "x": 19,
          "y": 16.043351807678665
        },
        {
          "x": 20,
          "y": 16.45699306524784
        },
        {
          "x": 21,
          "y": 16.462592881113547
        },
        {
          "x": 22,
          "y": 16.690332076876583
        },
        {
          "x": 23,
          "y": 16.862986986094604
        },
        {
          "x": 24,
          "y": 16.901308140834168
        },
        {
          "x": 25,
          "y": 17.205306208625863
        },
        {
          "x": 26,
          "y": 17.33516529775154
        },
        {
          "x": 27,
          "y": 17.381231178020045
        },
        {
          "x": 28,
          "y": 17.42674659753285
        },
        {
          "x": 29,
          "y": 17.478220976280525
        },
        {
          "x": 30,
          "y": 17.499767301102846
        },
        {
          "x": 31,
          "y": 17.500230747069068
        },
        {
          "x": 32,
          "y": 17.48789671367088
        },
        {
          "x": 33,
          "y": 17.427973926553502
        },
        {
          "x": 34,
          "y": 17.38031019904881
        },
        {
          "x": 35,
          "y": 17.338918848565115
        },
        {
          "x": 36,
          "y": 17.363778964124972
        },
        {
          "x": 37,
          "y": 17.352807557349646
        },
        {
          "x": 38,
          "y": 17.365164742154363
        },
        {
          "x": 39,
          "y": 17.396802477158914
        },
        {
          "x": 40,
          "y": 17.42176776804293
        },
        {
          "x": 41,
          "y": 17.46120741603453
        },
        {
          "x": 42,
          "y": 17.479680882979224
        },
        {
          "x": 43,
          "y": 17.50140037554821
        },
        {
          "x": 44,
          "y": 17.570876705743853
        },
        {
          "x": 45,
          "y": 17.653335832359872
        },
        {
          "x": 46,
          "y": 17.672590027000247
        },
        {
          "x": 47,
          "y": 17.69009320982334
        },
        {
          "x": 48,
          "y": 17.715904776649502
        },
        {
          "x": 49,
          "y": 17.727554828673835
        }
      ]
    },
    {
      "label": "seed_110",
      "data": [
        {
          "x": 0,
          "y": 6.625215903583139
        },
        {
          "x": 1,
          "y": 10.19389659994122
        },
        {
          "x": 2,
          "y": 12.09254460381611
        },
        {
          "x": 3,
          "y": 12.673471328719613
        },
        {
          "x": 4,
          "y": 13.876789064464171
        },
        {
          "x": 5,
          "y": 14.332286072819464
        },
        {
          "x": 6,
          "y": 14.367586914392673
        },
        {
          "x": 7,
          "y": 14.501103540808067
        },
        {
          "x": 8,
          "y": 14.537592809749013
        },
        {
          "x": 9,
          "y": 14.64987486217482
        },
        {
          "x": 10,
          "y": 14.923815344538484
        },
        {
          "x": 11,
          "y": 15.079566309267353
        },
        {
          "x": 12,
          "y": 15.117129976337685
        },
        {
          "x": 13,
          "y": 14.936393098248196
        },
        {
          "x": 14,
          "y": 14.782428508186324
        },
        {
          "x": 15,
          "y": 14.683475150177475
        },
        {
          "x": 16,
          "y": 14.632559238083216
        },
        {
          "x": 17,
          "y": 14.68801540679154
        },
        {
          "x": 18,
          "y": 14.885709524827902
        },
        {
          "x": 19,
          "y": 15.047047993819096
        },
        {
          "x": 20,
          "y": 15.284387896050482
        },
        {
          "x": 21,
          "y": 15.300955177903406
        },
        {
          "x": 22,
          "y": 15.301833098286728
        },
        {
          "x": 23,
          "y": 15.41167875127732
        },
        {
          "x": 24,
          "y": 15.754166816094797
        },
        {
          "x": 25,
          "y": 16.04555169023988
        },
        {
          "x": 26,
          "y": 16.32256942823276
        },
        {
          "x": 27,
          "y": 16.42969236555239
        },
        {
          "x": 28,
          "y": 16.400264663616568
        },
        {
          "x": 29,
          "y": 16.362939857382447
        },
        {
          "x": 30,
          "y": 16.46937600547159
        },
        {
          "x": 31,
          "y": 16.46644226894257
        },
        {
          "x": 32,
          "y": 16.507773173979963
        },
        {
          "x": 33,
          "y": 16.510472227618934
        },
        {
          "x": 34,
          "y": 16.560757104497824
        },
        {
          "x": 35,
          "y": 16.60802525582315
        },
        {
          "x": 36,
          "y": 16.631274057379184
        },
        {
          "x": 37,
          "y": 16.730557136415477
        },
        {
          "x": 38,
          "y": 16.801448602352945
        },
        {
          "x": 39,
          "y": 16.944404309369027
        },
        {
          "x": 40,
          "y": 16.939806522269894
        },
        {
          "x": 41,
          "y": 16.914158527086443
        },
        {
          "x": 42,
          "y": 16.89872284819671
        },
        {
          "x": 43,
          "y": 16.89399382020563
        },
        {
          "x": 44,
          "y": 16.8786835801534
        },
        {
          "x": 45,
          "y": 16.889788609682125
        },
        {
          "x": 46,
          "y": 16.933898840557937
        },
        {
          "x": 47,
          "y": 16.952619937720755
        },
        {
          "x": 48,
          "y": 16.962927942789694
        },
        {
          "x": 49,
          "y": 16.981847947478066
        }
      ]
    },
    {
      "label": "seed_10",
      "data": [
        {
          "x": 0,
          "y": 7.139104821494122
        },
        {
          "x": 1,
          "y": 9.869095433436186
        },
        {
          "x": 2,
          "y": 12.245073752691372
        },
        {
          "x": 3,
          "y": 12.27998384153234
        },
        {
          "x": 4,
          "y": 12.498048193726571
        },
        {
          "x": 5,
          "y": 13.567551177952726
        },
        {
          "x": 6,
          "y": 13.967564883411049
        },
        {
          "x": 7,
          "y": 14.483791868942902
        },
        {
          "x": 8,
          "y": 14.80713949017072
        },
        {
          "x": 9,
          "y": 14.984999135563744
        },
        {
          "x": 10,
          "y": 14.990326491324264
        },
        {
          "x": 11,
          "y": 14.972295175301522
        },
        {
          "x": 12,
          "y": 14.850583504888398
        },
        {
          "x": 13,
          "y": 14.823767681580962
        },
        {
          "x": 14,
          "y": 14.755763146264051
        },
        {
          "x": 15,
          "y": 14.75566905291237
        },
        {
          "x": 16,
          "y": 14.840199477536244
        },
        {
          "x": 17,
          "y": 15.092747904776708
        },
        {
          "x": 18,
          "y": 15.445780449660331
        },
        {
          "x": 19,
          "y": 15.660023178914372
        },
        {
          "x": 20,
          "y": 15.82062583015388
        },
        {
          "x": 21,
          "y": 15.939650932648966
        },
        {
          "x": 22,
          "y": 16.12898647221988
        },
        {
          "x": 23,
          "y": 16.2327919542627
        },
        {
          "x": 24,
          "y": 16.554172156386077
        },
        {
          "x": 25,
          "y": 16.779986034006765
        },
        {
          "x": 26,
          "y": 16.84194291743861
        },
        {
          "x": 27,
          "y": 17.041192061371966
        },
        {
          "x": 28,
          "y": 17.123826088822653
        },
        {
          "x": 29,
          "y": 17.23070209595417
        },
        {
          "x": 30,
          "y": 17.50461615247179
        },
        {
          "x": 31,
          "y": 17.742258427712713
        },
        {
          "x": 32,
          "y": 17.884608945955428
        },
        {
          "x": 33,
          "y": 18.020059812511278
        },
        {
          "x": 34,
          "y": 17.99668489509027
        },
        {
          "x": 35,
          "y": 17.985914629381533
        },
        {
          "x": 36,
          "y": 17.934316176823152
        },
        {
          "x": 37,
          "y": 17.950195868880048
        },
        {
          "x": 38,
          "y": 17.94763993490949
        },
        {
          "x": 39,
          "y": 17.949564025703793
        },
        {
          "x": 40,
          "y": 17.95170360894793
        },
        {
          "x": 41,
          "y": 17.95841938299211
        },
        {
          "x": 42,
          "y": 17.96910171442524
        },
        {
          "x": 43,
          "y": 17.97874343121054
        },
        {
          "x": 44,
          "y": 17.987624837273188
        },
        {
          "x": 45,
          "y": 17.993908045635088
        },
        {
          "x": 46,
          "y": 17.99397875652696
        },
        {
          "x": 47,
          "y": 17.98957269133492
        },
        {
          "x": 48,
          "y": 17.989290851571518
        },
        {
          "x": 49,
          "y": 17.988125479887564
        }
      ]
    },
    {
      "label": "seed_1",
      "data": [
        {
          "x": 0,
          "y": 6.08521134214417
        },
        {
          "x": 1,
          "y": 10.066805209283457
        },
        {
          "x": 2,
          "y": 13.16873593122421
        },
        {
          "x": 3,
          "y": 23.50055306978858
        },
        {
          "x": 4,
          "y": 23.71339285148582
        },
        {
          "x": 5,
          "y": 23.46941684046489
        },
        {
          "x": 6,
          "y": 24.26062848536114
        },
        {
          "x": 7,
          "y": 26.011185091458696
        },
        {
          "x": 8,
          "y": 26.96703718751972
        },
        {
          "x": 9,
          "y": 27.48425243733792
        },
        {
          "x": 10,
          "y": 28.468870024245845
        },
        {
          "x": 11,
          "y": 28.47983526494194
        },
        {
          "x": 12,
          "y": 28.805475386139527
        },
        {
          "x": 13,
          "y": 28.610464364572984
        },
        {
          "x": 14,
          "y": 27.53590947535841
        },
        {
          "x": 15,
          "y": 26.36933538700477
        },
        {
          "x": 16,
          "y": 26.22862423497843
        },
        {
          "x": 17,
          "y": 26.533755828901658
        },
        {
          "x": 18,
          "y": 26.89269261167754
        },
        {
          "x": 19,
          "y": 26.895771443077336
        },
        {
          "x": 20,
          "y": 26.88835766929452
        },
        {
          "x": 21,
          "y": 26.91244981804253
        },
        {
          "x": 22,
          "y": 26.950617682718807
        },
        {
          "x": 23,
          "y": 26.96062175333713
        },
        {
          "x": 24,
          "y": 27.007217935750823
        },
        {
          "x": 25,
          "y": 27.01649871193976
        },
        {
          "x": 26,
          "y": 27.025610636224684
        },
        {
          "x": 27,
          "y": 26.99504946110393
        },
        {
          "x": 28,
          "y": 26.995762854182143
        },
        {
          "x": 29,
          "y": 27.011918891659768
        },
        {
          "x": 30,
          "y": 27.03259603398332
        },
        {
          "x": 31,
          "y": 27.054329145694208
        },
        {
          "x": 32,
          "y": 27.078343616045743
        },
        {
          "x": 33,
          "y": 27.094561251200684
        },
        {
          "x": 34,
          "y": 27.117971121176737
        },
        {
          "x": 35,
          "y": 27.10687496620956
        },
        {
          "x": 36,
          "y": 27.104090710059857
        },
        {
          "x": 37,
          "y": 27.10115031441136
        },
        {
          "x": 38,
          "y": 27.12125790257267
        },
        {
          "x": 39,
          "y": 27.1555315448183
        },
        {
          "x": 40,
          "y": 27.221926192767377
        },
        {
          "x": 41,
          "y": 27.29567825918077
        },
        {
          "x": 42,
          "y": 27.35909925776549
        },
        {
          "x": 43,
          "y": 27.545919045081767
        },
        {
          "x": 44,
          "y": 27.847738868743797
        },
        {
          "x": 45,
          "y": 28.19321729409307
        },
        {
          "x": 46,
          "y": 28.873719653094675
        },
        {
          "x": 47,
          "y": 29.444660211374632
        },
        {
          "x": 48,
          "y": 30.12539538699683
        },
        {
          "x": 49,
          "y": 30.802976842631235
        }
      ]
    },
    {
      "label": "seed_0",
      "data": [
        {
          "x": 0,
          "y": 6.024976981664581
        },
        {
          "x": 1,
          "y": 10.38645606179954
        },
        {
          "x": 2,
          "y": 16.200996744315155
        },
        {
          "x": 3,
          "y": 29.03326549524458
        },
        {
          "x": 4,
          "y": 36.818122791672266
        },
        {
          "x": 5,
          "y": 38.44401835988563
        },
        {
          "x": 6,
          "y": 39.3244080172522
        },
        {
          "x": 7,
          "y": 38.87139370393505
        },
        {
          "x": 8,
          "y": 38.8824562527748
        },
        {
          "x": 9,
          "y": 41.51040245038034
        },
        {
          "x": 10,
          "y": 42.65017733165898
        },
        {
          "x": 11,
          "y": 46.25065664900129
        },
        {
          "x": 12,
          "y": 50.78179960652881
        },
        {
          "x": 13,
          "y": 59.98666458858772
        },
        {
          "x": 14,
          "y": 65.64152792471687
        },
        {
          "x": 15,
          "y": 66.12758566397049
        },
        {
          "x": 16,
          "y": 73.40877276581291
        },
        {
          "x": 17,
          "y": 76.50803397920455
        },
        {
          "x": 18,
          "y": 78.31135713513835
        },
        {
          "x": 19,
          "y": 86.80477568634075
        },
        {
          "x": 20,
          "y": 91.26709952151651
        },
        {
          "x": 21,
          "y": 99.8607441561148
        },
        {
          "x": 22,
          "y": 102.1269476374207
        },
        {
          "x": 23,
          "y": 103.94306253705015
        },
        {
          "x": 24,
          "y": 110.90023810217784
        },
        {
          "x": 25,
          "y": 116.95873792543742
        },
        {
          "x": 26,
          "y": 121.76402029503262
        },
        {
          "x": 27,
          "y": 120.8232669266568
        },
        {
          "x": 28,
          "y": 122.08459167734968
        },
        {
          "x": 29,
          "y": 125.65536393440324
        },
        {
          "x": 30,
          "y": 125.96117245125784
        },
        {
          "x": 31,
          "y": 126.16227175721949
        },
        {
          "x": 32,
          "y": 128.21123402718496
        },
        {
          "x": 33,
          "y": 136.05974031956256
        },
        {
          "x": 34,
          "y": 136.91343572107257
        },
        {
          "x": 35,
          "y": 150.85553649559026
        },
        {
          "x": 36,
          "y": 157.68236814415337
        },
        {
          "x": 37,
          "y": 159.5729135891686
        },
        {
          "x": 38,
          "y": 164.30383491529778
        },
        {
          "x": 39,
          "y": 164.8016892810057
        },
        {
          "x": 40,
          "y": 165.21596326822734
        },
        {
          "x": 41,
          "y": 166.36924018698926
        },
        {
          "x": 42,
          "y": 164.96236068068362
        },
        {
          "x": 43,
          "y": 164.25140732785366
        },
        {
          "x": 44,
          "y": 166.1815480880678
        },
        {
          "x": 45,
          "y": 165.65314738995244
        },
        {
          "x": 46,
          "y": 168.1932911316681
        },
        {
          "x": 47,
          "y": 166.6194486515131
        },
        {
          "x": 48,
          "y": 169.40081568900763
        },
        {
          "x": 49,
          "y": 169.7372720639014
        }
      ]
    },
    {
      "label": "seed_4",
      "data": [
        {
          "x": 0,
          "y": 6.05383863270017
        },
        {
          "x": 1,
          "y": 7.195051336448538
        },
        {
          "x": 2,
          "y": 10.992275167734237
        },
        {
          "x": 3,
          "y": 13.269320150474504
        },
        {
          "x": 4,
          "y": 13.360116759734646
        },
        {
          "x": 5,
          "y": 12.953725516788984
        },
        {
          "x": 6,
          "y": 13.752162104490663
        },
        {
          "x": 7,
          "y": 14.245995852462777
        },
        {
          "x": 8,
          "y": 14.668882686547354
        },
        {
          "x": 9,
          "y": 15.791817580010411
        },
        {
          "x": 10,
          "y": 15.884298478830468
        },
        {
          "x": 11,
          "y": 15.844870592993091
        },
        {
          "x": 12,
          "y": 15.775012215230095
        },
        {
          "x": 13,
          "y": 15.345045944832746
        },
        {
          "x": 14,
          "y": 15.343053201185167
        },
        {
          "x": 15,
          "y": 15.477123303071998
        },
        {
          "x": 16,
          "y": 15.491891252119135
        },
        {
          "x": 17,
          "y": 15.489442091899232
        },
        {
          "x": 18,
          "y": 15.479730384094028
        },
        {
          "x": 19,
          "y": 15.836652925036066
        },
        {
          "x": 20,
          "y": 15.913676218876764
        },
        {
          "x": 21,
          "y": 15.930255949083604
        },
        {
          "x": 22,
          "y": 16.034579469725955
        },
        {
          "x": 23,
          "y": 16.119249925982146
        },
        {
          "x": 24,
          "y": 16.25584898345866
        },
        {
          "x": 25,
          "y": 16.284411031481486
        },
        {
          "x": 26,
          "y": 16.4140328655623
        },
        {
          "x": 27,
          "y": 16.519905024404405
        },
        {
          "x": 28,
          "y": 16.91185009936
        },
        {
          "x": 29,
          "y": 17.10089063289596
        },
        {
          "x": 30,
          "y": 17.138571638589024
        },
        {
          "x": 31,
          "y": 17.238455129946264
        },
        {
          "x": 32,
          "y": 17.332274655227486
        },
        {
          "x": 33,
          "y": 17.293619776114486
        },
        {
          "x": 34,
          "y": 17.067243097485765
        },
        {
          "x": 35,
          "y": 16.788607950498236
        },
        {
          "x": 36,
          "y": 16.739454250334784
        },
        {
          "x": 37,
          "y": 16.66035349418141
        },
        {
          "x": 38,
          "y": 16.586405566991626
        },
        {
          "x": 39,
          "y": 16.551451153009364
        },
        {
          "x": 40,
          "y": 16.528110920492413
        },
        {
          "x": 41,
          "y": 16.550773119181706
        },
        {
          "x": 42,
          "y": 16.588080832158738
        },
        {
          "x": 43,
          "y": 16.580610486956154
        },
        {
          "x": 44,
          "y": 16.59464995154438
        },
        {
          "x": 45,
          "y": 16.611160997442212
        },
        {
          "x": 46,
          "y": 16.641677605831102
        },
        {
          "x": 47,
          "y": 16.6883816089545
        },
        {
          "x": 48,
          "y": 16.73769345237934
        },
        {
          "x": 49,
          "y": 16.75349978366692
        }
      ]
    }
  ]
}